Metadata-Version: 2.1
Name: odoo14-addon-pos_require_product_quantity
Version: 14.0.1.0.1.dev12
Summary: A popup is shown if product quantity is set to 0 for one or more order lines when clicking on "Payment" button.
Home-page: https://github.com/OCA/pos
Author: Coop IT Easy SCRLfs, Odoo Community Association (OCA)
Author-email: support@odoo-community.org
License: AGPL-3
Classifier: Programming Language :: Python
Classifier: Framework :: Odoo
Classifier: Framework :: Odoo :: 14.0
Classifier: License :: OSI Approved :: GNU Affero General Public License v3
Requires-Python: >=3.6
Requires-Dist: odoo<14.1dev,>=14.0a
